channeltoy/__init__.py
channeltoy/channeltoy.py
channeltoy/cli.py
channeltoy-0.1.0.dist-info/AUTHORS.rst
channeltoy-0.1.0.dist-info/LICENSE
channeltoy-0.1.0.dist-info/METADATA
channeltoy-0.1.0.dist-info/WHEEL
channeltoy-0.1.0.dist-info/entry_points.txt
channeltoy-0.1.0.dist-info/top_level.txt
channeltoy-0.1.0.dist-info/RECORD
