Metadata-Version: 2.1
Name: channeltoy
Version: 0.1.0
Summary: A collection of tools for exploring channel evolution.
Home-page: https://github.com/simon-m-mudd/channeltoy
Author: Simon M Mudd
Author-email: simon.m.mudd@ed.ac.uk
License: MIT license
Keywords: channeltoy
Platform: UNKNOWN
Classifier: Development Status :: 2 - Pre-Alpha
Classifier: Intended Audience :: Developers
Classifier: License :: OSI Approved :: MIT License
Classifier: Natural Language :: English
Classifier: Programming Language :: Python :: 3
Classifier: Programming Language :: Python :: 3.6
Classifier: Programming Language :: Python :: 3.7
Classifier: Programming Language :: Python :: 3.8
Requires-Python: >=3.5
Requires-Dist: Click (>=7.0)
